supercharge/__init__.py
supercharge/base.py
supercharge/charge.py
tests/__init__.py
tests/test_base.py
tests/test_charge.py
supercharge-0.1.0.dist-info/LICENSE
supercharge-0.1.0.dist-info/METADATA
supercharge-0.1.0.dist-info/WHEEL
supercharge-0.1.0.dist-info/top_level.txt
supercharge-0.1.0.dist-info/RECORD
