Metadata-Version: 2.1
Name: supercharge
Version: 0.1.0
Summary: Expand Python Super Capabilities
Home-page: https://github.com/zincware/supercharge
Author: zincwarecode
Author-email: zincwarecode@gmail.com
License: UNKNOWN
Download-URL: https://github.com/zincware/supercharge/archive/beta.tar.gz
Keywords: super,inheritance,ZnTrack
Platform: UNKNOWN
Classifier: Development Status :: 3 - Alpha
Classifier: Programming Language :: Python :: 3
Classifier: License :: OSI Approved :: Eclipse Public License 2.0 (EPL-2.0)
Classifier: Operating System :: OS Independent
Requires-Python: >=3.7
License-File: LICENSE
